butterfree/__init__.py
butterfree/_cli/__init__.py
butterfree/_cli/main.py
butterfree/_cli/migrate.py
butterfree/automated/__init__.py
butterfree/automated/feature_set_creation.py
butterfree/clients/__init__.py
butterfree/clients/abstract_client.py
butterfree/clients/cassandra_client.py
butterfree/clients/spark_client.py
butterfree/configs/__init__.py
butterfree/configs/environment.py
butterfree/configs/db/__init__.py
butterfree/configs/db/abstract_config.py
butterfree/configs/db/cassandra_config.py
butterfree/configs/db/delta.py
butterfree/configs/db/kafka_config.py
butterfree/configs/db/metastore_config.py
butterfree/constants/__init__.py
butterfree/constants/columns.py
butterfree/constants/data_type.py
butterfree/constants/migrations.py
butterfree/constants/spark_constants.py
butterfree/constants/window_definitions.py
butterfree/dataframe_service/__init__.py
butterfree/dataframe_service/incremental_strategy.py
butterfree/dataframe_service/partitioning.py
butterfree/dataframe_service/repartition.py
butterfree/extract/__init__.py
butterfree/extract/source.py
butterfree/extract/pre_processing/__init__.py
butterfree/extract/pre_processing/explode_json_column_transform.py
butterfree/extract/pre_processing/filter_transform.py
butterfree/extract/pre_processing/forward_fill_transform.py
butterfree/extract/pre_processing/pivot_transform.py
butterfree/extract/pre_processing/replace_transform.py
butterfree/extract/readers/__init__.py
butterfree/extract/readers/file_reader.py
butterfree/extract/readers/kafka_reader.py
butterfree/extract/readers/reader.py
butterfree/extract/readers/table_reader.py
butterfree/hooks/__init__.py
butterfree/hooks/hook.py
butterfree/hooks/hookable_component.py
butterfree/hooks/schema_compatibility/__init__.py
butterfree/hooks/schema_compatibility/cassandra_table_schema_compatibility_hook.py
butterfree/hooks/schema_compatibility/spark_table_schema_compatibility_hook.py
butterfree/load/__init__.py
butterfree/load/sink.py
butterfree-1.8.0.dist-info/LICENSE
butterfree-1.8.0.dist-info/METADATA
butterfree-1.8.0.dist-info/WHEEL
butterfree-1.8.0.dist-info/entry_points.txt
butterfree-1.8.0.dist-info/top_level.txt
butterfree-1.8.0.dist-info/RECORD
