Metadata-Version: 2.1
Name: butterfree
Version: 1.8.0
Summary: A tool for building feature stores - Transform your raw data into beautiful features.
Home-page: https://github.com/quintoandar/butterfree
Author: QuintoAndar
License: Copyright
Keywords: feature store sets ETL
Platform: UNKNOWN
Requires-Python: >=3.9, <4
License-File: LICENSE
Requires-Dist: cassandra-driver==3.24.0
Requires-Dist: mdutils<1.7,>=1.2.2
Requires-Dist: pandas<2.0,>=0.24
Requires-Dist: parameters-validation<2.0,>=1.1.5
Requires-Dist: pyspark==3.5.1
Requires-Dist: typer==0.4.2
Requires-Dist: typing-extensions<5,>3.7.4
Requires-Dist: boto3==1.35.*
Requires-Dist: numpy==1.26.4
Requires-Dist: delta-spark==3.2.0
Requires-Dist: pydantic
Provides-Extra: h3
Requires-Dist: h3<4,>=3.7.4; extra == "h3"
